LICENSE
README.md
setup.py
flask_doc_z/__init__.py
flask_doc_z/describer.py
flask_doc_z/gen_template.html
flask_doc_z/generator.py
flask_doc_z/loading.gif
flask_doc_z/utils.py
flask_doc_z.egg-info/PKG-INFO
flask_doc_z.egg-info/SOURCES.txt
flask_doc_z.egg-info/dependency_links.txt
flask_doc_z.egg-info/entry_points.txt
flask_doc_z.egg-info/not-zip-safe
flask_doc_z.egg-info/requires.txt
flask_doc_z.egg-info/top_level.txt