Metadata-Version: 2.1
Name: flask-doc-z
Version: 0.0.3
Summary: Simple Flask API doc generator，forked from https://github.com/ipconfiger/flask-apidoc
Home-page: 
Author: Zhong.PengQun
Author-email: 
License-File: LICENSE
